{
  "experiment_id": "haiku45_two_try_no_reflection_case2_run3",
  "model": "haiku45",
  "config": "two_try_no_reflection",
  "case_id": "case2",
  "run_id": 3,
  "success": true,
  "trials_used": 1,
  "final_status": "Replaced",
  "total_time": 46.027655363082886,
  "total_cost": 0.10073985,
  "total_tokens": 1270,
  "trial_details": [
    {
      "trial": 1,
      "success": true,
      "pod_status": "Replaced",
      "eval_reason": "Deployment healthy with 2/2 replicas",
      "actor_time": 40.47916793823242,
      "eval_time": 5.548367738723755,
      "reflection_time": 0.0,
      "actor_cost": 0.10073985,
      "reflection_cost": 0.0,
      "actor_input_tokens": 17,
      "actor_output_tokens": 1253,
      "actor_cache_read_tokens": 114516,
      "actor_cache_creation_tokens": 4914,
      "reflection_tokens": 0,
      "trajectory": "I'll help you diagnose and fix the Kubernetes pod. Let me start by examining the pod's current state.## DIAGNOSIS\n\n**Problem**: The pod is in `ErrImageNeverPull` status because:\n- The container image is `incorrect-selector-app:latest` which doesn't exist\n- The pull policy is set to \"Never\", so Kubernetes won't try to pull the image\n- The image name appears to be incorrect/incomplete\n\nI need to check the Deployment to understand the correct image and then fix it:The Deployment has two issues:\n1. Image name is wrong: `incorrect-selector-app:latest` \n2. ImagePullPolicy is `Never` which prevents pulling any image\n\nLet me check what images are available locally:Let me check available images:Perfect! I can see both `incorrect-selector-app` and `correct-selector-app` are available. The problem is the Deployment is using the wrong image. The image `incorrect-selector-app:latest` exists but the name suggests it's the wrong one to use. Let me patch the Deployment to fix the image and also change the imagePullPolicy to \"IfNotPresent\":The Deployment has been patched. This will trigger a rolling update which will create new pods. The fix is complete.\n\n## SUMMARY\n\n**What was wrong:**\n- Pod was in `ErrImageNeverPull` status\n- The Deployment was using the wrong image: `incorrect-selector-app:latest` \n- The imagePullPolicy was set to \"Never\" which prevents image pulling\n\n**What I fixed:**\n1. Patched the Deployment to use the correct image: `correct-selector-app:latest`\n2. Changed imagePullPolicy from \"Never\" to \"IfNotPresent\" to allow proper image handling\n3. The Deployment will now roll out new pods with the correct image\n\n**FIX COMPLETE**\n\n## COMMANDS EXECUTED:\n1. $ kubectl get pod myapp-deployment-6788c9c89d-4m7pc -n case2-test\n   Output: NAME                                READY   STATUS              RESTARTS   AGE\nmyapp-deployment-6788c9c89d-4m7pc   0/1     ErrImageNeverPull   0          13s...\n2. $ kubectl describe pod myapp-deployment-6788c9c89d-4m7pc -n case2-test\n   Output: Name:             myapp-deployment-6788c9c89d-4m7pc\nNamespace:        case2-test\nPriority:         0\nService Account:  default\nNode:             minikube/192.168.49.2\nStart Time:       Thu, 25 Dec 202...\n3. $ kubectl logs myapp-deployment-6788c9c89d-4m7pc -n case2-test\n   Output: Exit code 1\nError from server (BadRequest): container \"myapp\" in pod \"myapp-deployment-6788c9c89d-4m7pc\" is waiting to start: ErrImageNeverPull...\n4. $ kubectl get events -n case2-test\n   Output: LAST SEEN   TYPE      REASON              OBJECT                                   MESSAGE\n19s         Normal    Scheduled           pod/myapp-deployment-6788c9c89d-4m7pc    Successfully assigned case...\n5. $ kubectl get deployment -n case2-test -o yaml\n   Output: apiVersion: v1\nitems:\n- apiVersion: apps/v1\n  kind: Deployment\n  metadata:\n    annotations:\n      deployment.kubernetes.io/revision: \"1\"\n      kubectl.kubernetes.io/last-applied-configuration: |\n     ...\n6. $ kubectl get deployment myapp-deployment -n case2-test -o yaml | grep -A5 \"selector:\"\n   Output:   selector:\n    matchLabels:\n      app: myapp-v1\n  strategy:\n    rollingUpdate:\n      maxSurge: 25%...\n7. $ docker images | grep -i myapp\n8. $ docker images\n   Output: REPOSITORY                                                       TAG       IMAGE ID       CREATED        SIZE\nwrong-interface-app                                              latest    a67d3e3f93d4   ...\n9. $ kubectl patch deployment myapp-deployment -n case2-test --type='json' -p='[{\"op\": \"replace\", \"path\": \"/spec/template/spec/containers/0/image\", \"value\":\"correct-selector-app:latest\"},{\"op\": \"replace\", \"path\": \"/spec/template/spec/containers/0/imagePullPolicy\", \"value\":\"IfNotPresent\"}]'\n   Output: deployment.apps/myapp-deployment patched...",
      "commands": [
        {
          "command": "kubectl get pod myapp-deployment-6788c9c89d-4m7pc -n case2-test",
          "output": "NAME                                READY   STATUS              RESTARTS   AGE\nmyapp-deployment-6788c9c89d-4m7pc   0/1     ErrImageNeverPull   0          13s"
        },
        {
          "command": "kubectl describe pod myapp-deployment-6788c9c89d-4m7pc -n case2-test",
          "output": "Name:             myapp-deployment-6788c9c89d-4m7pc\nNamespace:        case2-test\nPriority:         0\nService Account:  default\nNode:             minikube/192.168.49.2\nStart Time:       Thu, 25 Dec 2025 05:13:23 +0300\nLabels:           app=myapp-v1\n                  pod-template-hash=6788c9c89d\n                  tier=frontend\nAnnotations:      <none>\nStatus:           Pending\nIP:               10.244.18.250\nIPs:\n  IP:           10.244.18.250\nControlled By:  ReplicaSet/myapp-deployment-6788c9c89d\n"
        },
        {
          "command": "kubectl logs myapp-deployment-6788c9c89d-4m7pc -n case2-test",
          "output": "Exit code 1\nError from server (BadRequest): container \"myapp\" in pod \"myapp-deployment-6788c9c89d-4m7pc\" is waiting to start: ErrImageNeverPull"
        },
        {
          "command": "kubectl get events -n case2-test",
          "output": "LAST SEEN   TYPE      REASON              OBJECT                                   MESSAGE\n19s         Normal    Scheduled           pod/myapp-deployment-6788c9c89d-4m7pc    Successfully assigned case2-test/myapp-deployment-6788c9c89d-4m7pc to minikube\n6s          Warning   ErrImageNeverPull   pod/myapp-deployment-6788c9c89d-4m7pc    Container image \"incorrect-selector-app:latest\" is not present with pull policy of Never\n6s          Warning   Failed              pod/myapp-deployment-6788c9c89d-4"
        },
        {
          "command": "kubectl get deployment -n case2-test -o yaml",
          "output": "apiVersion: v1\nitems:\n- apiVersion: apps/v1\n  kind: Deployment\n  metadata:\n    annotations:\n      deployment.kubernetes.io/revision: \"1\"\n      kubectl.kubernetes.io/last-applied-configuration: |\n        {\"apiVersion\":\"apps/v1\",\"kind\":\"Deployment\",\"metadata\":{\"annotations\":{},\"name\":\"myapp-deployment\",\"namespace\":\"case2-test\"},\"spec\":{\"replicas\":2,\"selector\":{\"matchLabels\":{\"app\":\"myapp-v1\"}},\"template\":{\"metadata\":{\"labels\":{\"app\":\"myapp-v1\",\"tier\":\"frontend\"}},\"spec\":{\"containers\":[{\"image\":\"in"
        },
        {
          "command": "kubectl get deployment myapp-deployment -n case2-test -o yaml | grep -A5 \"selector:\"",
          "output": "  selector:\n    matchLabels:\n      app: myapp-v1\n  strategy:\n    rollingUpdate:\n      maxSurge: 25%"
        },
        {
          "command": "docker images | grep -i myapp",
          "output": null
        },
        {
          "command": "docker images",
          "output": "REPOSITORY                                                       TAG       IMAGE ID       CREATED        SIZE\nwrong-interface-app                                              latest    a67d3e3f93d4   3 weeks ago    133MB\n<none>                                                           <none>    95476552f5bb   3 weeks ago    133MB\n<none>                                                           <none>    fa7a4b0ceaa1   3 weeks ago    133MB\ncascading-failure-app                                    "
        },
        {
          "command": "kubectl patch deployment myapp-deployment -n case2-test --type='json' -p='[{\"op\": \"replace\", \"path\": \"/spec/template/spec/containers/0/image\", \"value\":\"correct-selector-app:latest\"},{\"op\": \"replace\", \"path\": \"/spec/template/spec/containers/0/imagePullPolicy\", \"value\":\"IfNotPresent\"}]'",
          "output": "deployment.apps/myapp-deployment patched"
        }
      ],
      "reflection_content": ""
    }
  ],
  "timestamp": "2025-12-25T05:14:14.701568"
}